[
  {
    "turn": 1,
    "agent_utterance": "좋은 아침이에요! 현재 목표 G가 2.40이라고 하셨는데 이 수치가 어떤 의미인지와 오늘 집중하고 싶은 식습관은 무엇인가요?",
    "user_utterance": "I hear you, but I’m not changing my routine easily, especially at night. Give me something blunt and simple to try tonight."
  },
  {
    "turn": 2,
    "agent_utterance": "오늘 밤은 야식 없이 물 한 잔으로 마무리하는 가장 간단한 규칙을 시도해 보세요. 지금 바로 해볼 수 있을까요?",
    "user_utterance": "Got it. My eating is irregular and I’m not ready to change yet, but I’ll keep tracking and check in if I want to adjust."
  },
  {
    "turn": 3,
    "agent_utterance": "오늘 밤은 아주 간단하게: 야식 없이 물 한 잔으로 마무리하는 규칙을 지키는 데 초점을 맞춰보세요. 이미 추적 중이니, 작은 습관 하나를 꾸준히 유지하는 것이 더 효과적입니다. 필요하면 내일 목표를 2.0으로 살짝 낮춰 조정하겠습니다.",
    "user_utterance": "I hear your suggestion, but I’m not up for making changes tonight. I’ll handle it on my own when I’m ready.",
    "suggestion": 2.2760846965922346,
    "ground_truth_action": 1.7728807627679106,
    "compliance_raw": 0.8993592132351352,
    "compliance_ema": 0.9432270317688775,
    "goal": 2.389223758315422,
    "reward": 1.9252757753303342,
    "user_compliance_prob": 0.4203484227064005,
    "behavior_mean_before": 1.9979096274647223,
    "behavior_mean_after": 1.9955124820169559,
    "noise": -0.3419593162408054,
    "noise_std": 0.7155818927523195
  }
]