[
  {
    "turn": 0,
    "agent_utterance": "안녕하세요. 첫 만남으로, 현재 욕구 강도는 대략 2.95로 예측됩니다. BED 관리에 도움이 되도록, 단계적이고 현실적인 시작 플래너를 제시합니다.\n\n1) 식단 계획 (강도 맵핑 ~ 2.95 근처)\n- 규칙적인 식사 시각 고정: 아침/점심/저녁을 매일 같은 시간에 맞춰 섭취합니다.\n- 간식 관리: 예비 간식(요거트, 견과류 한 줌, 과일)을 미리 준비해 두고, 정해진 시간에만 섭취합니다.\n- 포만감 중심 구성: 단백질과 섬유질이 풍부한 식단으로 포만감을 지속합니다. 예: \n  - 아침: 그릭 요거트 + 베리류 + 견과\n  - 점심: 닭가슴살 또는 두부+통곡물(현미/퀴노아) + 채소\n  - 저녁: 생선 또는 두부 + 채소 샐러드 + 현미\n- 식사 전 물 한 잔: 식사 시작 1컵의 물을 마셔 포만감 유도 및 과식 예방.\n- 야간 간식 줄이기: 저녁 3시간",
    "agent_monologue": "Level 3.64 | Focus: Diet/Exercise | est_c=0.68",
    "user_utterance": "좋아, 계획 feels 실제적이고 관리 가능해 보여. 지금 욕구 강도는 High나 Low 중 어느 쪽이야? 지금은 대략 중간 수준인 2.5~3 쯤으로 들려서 식단 규칙 지키는 게 도움이 될 것 같아.\n\n- 다이어트 포맷은 그대로 유지하고, 특히 식사 간 규칙성과 간식 예비 준비가 좋네. 간식 예비를 미리 두는 전략은 지금 욕구를 잘 다독여 줄 거야.\n- 야간 간식 줄이는 목표도 착실히 진행하면 좋겠어. 저녁 3시간 전 물 한 컵은 지금 바로 시작 가능해.\n- 나는 지금 포만감 중심 식단이 도움이 될 것 같아. 아침 그릭 요거트+베리+견과, 점심 현",
    "suggestion_numeric": 3.6436003117411144
  },
  {
    "turn": 1,
    "agent_utterance": "좋아요. 현재 욕구 강도가 중간 수준(대략 2.5–3 정도)이라고 판단하니, High와 Moderate 사이의 계획으로 구성해 보겠습니다. 다이어트 포맷은 유지하고, 간식 예비 준비와 규칙적 식사를 중심으로 제시합니다.\n\n1) 식단 계획 (현 단계에 맞춘 SPECIFIC 계획)\n- 식사 규칙성\n  - 매일 3끼 규칙: 아침, 점심, 저녁 같은 간격으로 섭취. 간식은 점심-저녁 사이 또는 저녁 직후에만 허용.\n- 아침 (*. 포만감 중심)\n  - 예: 그릭 요거트 150–180g + 혼합 베리 한컵(딸기/블루베리/라즈베리) + 견과류 한 작은 주먹(아몬드/호두) + 꿀 조금(선택)\n  - 목표: 단백질+섬유소로 포만감 유지\n- 간식 예비(규칙적 간식 준비)\n  - 간식 예비 목록 2종 준비: \n    - 요거트 그릇형: 그릭 요거트 90g + 코티지 치즈 40g + 사과 슬라이스\n    - 간",
    "agent_monologue": "Level 3.64 | Focus: Diet/Exercise | est_c=0.68",
    "user_utterance": "좋아요. 현재 욕구 강도는 중간쯤인데, 식단은 다이어트 포맷으로 간식 예비와 규칙적 식사 중심이라 plan이 현실적으로 다가와요. 지금은 간식 예비 준비를 통해 욕구를 잘 눌러줄 수 있을 듯합니다. 나도 지금 binge 욕구는 높음에서 중간 쪽으로 가고 있어요.",
    "suggestion_numeric": 3.6436003117411144
  },
  {
    "turn": 2,
    "agent_utterance": "좋아요. 현재 욕구 강도 2.95 수준에 맞춰, 다이어트 포맷의 식단으로도 현실적으로 실천 가능하게, 간식 예비와 규칙적 식사를 중심으로 구체적인 PLAN을 제시합니다.\n\n1) 식단 plan (정확한 금식 창 없이도 실천 가능하도록)\n- 식사 규칙\n  - 규칙적 식사 3끼: 아침, 점심, 저녁을 동일한 시간대에 맞추되, 시간은 좌측으로 30분 내외 조정 가능하게 유지\n  - 매끼 단백질 20-25g 포함: 예) 닭가슴살 100-120g, 두부 150g, 달걀 2개, 콩류\n  - 섬유질 25-30g 포함: 현미밥 소량(1/2공기) 또는 통곡물빵 한 조각, 채소 다채롭게\n  - 건강한 지방: 올리브유 1-2큰술, 견과류 한 줌(20-30g) 주 4-5회\n- 간식 예비(욕구 관리 핵심)\n  - 간식 예비 2종 세트, 식사 사이 간격이 길어질 때 이용",
    "agent_monologue": "Level 3.64 | Focus: Diet/Exercise | est_c=0.68",
    "user_utterance": "좋아요! 계획은 현실적으로 들려서 실행 의욕이 생겨. 지금 욕구는 중간 정도인데(약 2.9/10 비슷), 간식 예비로 잘 관리할 수 있을 것 같아. 간식 예비 2종 세트 준비할게. 구체적으로는 아래처럼 행동해볼게.\n\n- 다이어트 식단: 매끼 규칙적 식사 유지, 단백질 20-25g 포함, 섬유질 25-30g, 건강한 지방 포함.\n- 간식 예비: 간식 예비 2종 중 하나는 단백질 위주로, 다른 하나는 채소+저지방식 간식으로.\n\n다 같이 실천해볼게. 욕구가 상승하면 간식 예비를 먼저 활용하고, 규칙적 식사 타임을 지",
    "suggestion_numeric": 3.6436003117411144
  },
  {
    "turn": 3,
    "agent_utterance": "좋아요. 현재 계획이 현실적이고 실행 의욕도 좋네요. 사용자의 욕구 수준(약 2.9/10)을 고려해, 3단계 강도에 맞춘 구체 PLAN을 제시합니다. 간식 예비 2종 세트 활용 전략과 함께, 식사 규칙성 유지에 초점을 맞출게요.\n\n1) 식단 계획 (3단계 강도에 맞춘 구체안)\n- 매끼 규칙적 식사 유지\n  - 식사 간격: 오전 8시, 오후 12시, 오후 6시 30분(주 7일 일관)\n  - 한 끼 구성: 단백질 20-25g, 섬유질 25-30g, 건강한 지방 포함\n  - 예시:\n    - 아침: 그릭요거트 150g + 견과류 15g + 과일 1종(예: 바나나 1/2개) + 통곡물 시리얼 30g\n    - 점심: 닭가슴살 120g + 현미 1/2공기 + 채소 샐러드 + 올리브오일 1큰술\n    - 저녁: 연어/두부 150g + 채소 볶음 +",
    "agent_monologue": "Level 3.64 | Focus: Diet/Exercise | est_c=0.68",
    "user_utterance": "좋아요! 식단 규칙성 유지 계획은 현실적이고 따라하기 쉬울 것 같아요. 현재 욕구 수준은 High 쪽으로 느껴져서, 간식 예비 2종 세트로 반드시 대비하겠습니다. 지금 욕구는 High 정도야. 이 PLAN이 어렵지 않게 느껴지고, 실행해나가면 가볍고 건강해지는 느낌이 기대돼요. 구체적으로는 다음이야:\n\n- 간식 예비 2종 세트 활용: 예비 간식으로 푼다발한 견과류+저당 과일, 혹은 요거트 한 컵과 당근스틱 같은 조합으로 배고픔 억제하기\n- 식사 규칙성 유지: 제시된 식사 간격과 한 끼 구성대로 흘러가도록 힘쓸",
    "suggestion_numeric": 3.6436003117411144
  },
  {
    "turn": 4,
    "agent_utterance": "좋아요. 현재 욕구가 High 쪽이라고 하셨으니, 바로 실행 가능한 3.0 ~ 4.0 수준의 план을 제시합니다. 식단 규칙성과 간식 대비를 중심으로 구체적 계획입니다.\n\n1) 식단 계획 (High ~ High-Plus 수준에 맞춘 구체 Plan)\n- 식사 간격: 3끼를 4시간 간격으로 유지 (예: 08:00, 12:00, 16:00) 또는 본인 루틴에 맞춰 조정\n- 한 끼 구성(모듈식 3요소):\n  - 단백질: 매 끼 25–30g\n  - 섬유질/복합탄수화물: 통곡물/채소 중심 1–2컵\n  - 건강한 지방: 소량의 견과류, 올리브유, 아보카도 등\n- 간식 예비 2종 세트 활용(핵심) \n  - 세트 A: 푼다발한 견과류 1줌(20–25g) + 저당 과일 1개(사과, 베리류) 또는 요거트 한 컵(무가당 그릭 요거트 150g) + 물 1컵",
    "agent_monologue": "Level 3.64 | Focus: Diet/Exercise | est_c=0.68",
    "user_utterance": "좋아, 실행 plan가 마음에 와닿아. 현재 욕구 High이니 간식 대비와 식단 규칙성에 집중해서 바로 해볼게. \n\n- 식단은 4시간 간격 3끼 유지(예: 08:00/12:00/16:00)로 시작하고, 한 끼당 단백질 25–30g, 섬유질/복합탄수화물 1–2컵, 건강한 지방 소량으로 구성하자.  \n- 간식은 세트 A로 준비: 견과류 한 줌(20–25g) + 저당 과일 하나 또는 무가당 그릭 요거트 150g + 물 한 컵.  \n- 현 시점 구체 행동: 오늘 아침 식사에 단백질 포함, 간식 A 하나를 두",
    "suggestion_numeric": 3.6436003117411144
  },
  {
    "turn": 5,
    "agent_utterance": "좋아요. 현재 욕구가 높다고 하셨으니, 간식 관리와 식단 규칙성에 집중하는 구체 계획을 제시합니다.\n\n1) 식단 계획 (4시간 간격 3끼 유지, 08:00/12:00/16:00)\n- 한 끼 구성(단백질 25–30g, 섬유질/복합탄수화물 1–2컵, 건강한 지방 소량)\n  - 08:00 (아침)\n    - 단백질: 계란 2개 또는 그릭 요거트 150–200g\n    - 섬유질/복합탄수화물: 오트밀 1/2컵(또는 현미밥 1/2공기) + 채소 한 접시\n    - 건강한 지방: 올리브오일 1작은술 또는 아몬드 6–8알\n  - 12:00 (점심)\n    - 단백질: 닭가슴살 100–120g 또는 두부 150g\n    - 섬유질/복합탄수화물: 현미밥 1/2공기 또는 퀴노아 1/2컵\n    - 채소: 다양한 생채소(샐",
    "agent_monologue": "Level 3.64 | Focus: Diet/Exercise | est_c=0.68",
    "user_utterance": "좋아요! 다이어트 계획이 구체적이라 떨어뜨릴 걱정 없이 바로 따라갈 수 있을 것 같아. 지금 욕구는 높지만, 간식 관리와 규칙적인 식단이 실천 가능해 보여. 현재 단식 욕구는 High이고, 간식 유혹이 당장 느껴져. 계획대로 08:00/12:00/16:00 4시간 간격 유지해서 한 끼당 단백질 충분히 챙기고, 채소랑 복합탄수화물도 함께 먹으면 버티기 수월할 거야.",
    "suggestion_numeric": 3.6436003117411144
  },
  {
    "turn": 6,
    "agent_utterance": "좋아요. 현재 상태와 욕구를 반영해, 강도 3.0~4.0 사이의 고강도 계획으로 구성했습니다.\n\n제안 plan (Diet & Exercise)\n- 식사 간격: 08:00 / 12:00 / 16:00 세 끼, 간식 없이 식사로 해결. 각 끼당 단백질+섬유질+복합탄수화물 비율 유지.\n- 단백질 목표: 각 끼 25–35g 단백질\n- 채소/복합탄수화물: 끼마다 2–3종 채소 + 현미/퀴노아/귀리 등 복합탄수화물 1종\n- 간식 관리: 현재 욕구가 강해도 4시간 간격 유지로 간식 유혹을 줄이고, 필요 시 200kcal 이내의 구조화된 미니 간식(예: 그릭요거트 150–180g + 견과류 한 줌 10–15g)으로 대체 가능. 다만 의도적으로 “간식”으로 두지 않고 끼니 구성으로 충족하는 방향.\n\n1) 식단 예시 (하루 계획)\n- 08:00 첫 끼\n  - 달걀 2개 또는",
    "agent_monologue": "Level 3.64 | Focus: Diet/Exercise | est_c=0.68",
    "user_utterance": "좋아요. 현재 욕구가 강한 편인데도 식사 간격 유지 계획이 구체적이라 마음가볍게 따라갈 수 있을 것 같아. 지금은 간식 욕구가 High 느낌이야. 다만 4시간 간격 유지로 간식 유혹을 줄이는 게 좋겠네. 오늘 식단 예시 잘 따라가볼게.",
    "suggestion_numeric": 3.6436003117411144
  },
  {
    "turn": 7,
    "agent_utterance": "좋아요. 현재 욕구가 강하고 간식 유혹이 높아도, 4시간 간격 식사로 간식 욕구를 관리하는 계획이 현실적이에요. 아래는 당신의 현재 수준(약 3.0대)과 목표에 맞춘 SPECIFIC 계획입니다.\n\n1) 식단 계획 (대략 4시간 간격, 고단백/섬유 중심)\n- 아침(07:30~08:00): 단백질 20–25g 포함 식사 예시\n  - 예: 그릭요거트 150g + 귀리 30g + 블루베리 한 줌 + 견과류 1큰술\n- 간식 1(11:30~12:00): 견과류+과일 조합 또는 단백질 간식\n  - 예: 사과 1개 + 아몬드 12–15알 또는 단백질 바 1개(선택)\n- 점심(12:30~13:30): 단백질 중심 + 채소 + 복합탄수화물\n  - 예: 닭가슴살 120–150g + 채소 샐러드 + 현미 또는 퀴노아 1/2컵\n- 간식 2(16:00~16:30",
    "agent_monologue": "Level 3.64 | Focus: Diet/Exercise | est_c=0.68",
    "user_utterance": "좋아요. 식단은 4시간 간격으로 잘 잡혔고 고단백/섬유 중심이라 정말 현실적이네요. 현재 간식 욕구가 꽤 강한 편인데도 이 계획으로 관리 가능하다고 느껴져요. 지금 욕구는 High로 올라왔지만, 간식 2-3번 정도의 조절로도 이 계획이 도움이 될 것 같아요.",
    "suggestion_numeric": 3.6436003117411144
  },
  {
    "turn": 8,
    "agent_utterance": "좋아요. 현재 계획이 현실적이고 지속 가능하다고 느끼신다면, 욕구 강도를 고려해 3.0 ~ 3.5 수준의 고강도 전환으로 다가가되, 실제 실행은 3단계( Moderate-High) 범주에 맞춰 점진적으로 진행하겠습니다.\n\n1) SPECIFIC PLAN (Diet & Exercise) — 현재 레벨 2.95에 맞춘 3.2 ~ 3.4 근접 계획\n\n- 식단(고강도에 맞춘 3.5 근접)\n  - 식사 간격: 4시간 간격 유지(예: 08:00 / 12:00 / 16:00 / 20:00)\n  - 한 끼당 단백질 25–30g 이상 포함, 섬유질 5–8g 추가(채소 다채롭게)\n  - 간식 관리: 간식은 하루 1회, 소량으로 제한하고, 가능하면 단백질+섬유가 높은 간식으로 대체\n    - 예: 그릭요거트 150g + 견과류 한 줌, 또는 사과+땅콩버터 1작은술\n  - 야간 간식 방지 전략: 잠자기 2시간 전 물 1",
    "agent_monologue": "Level 3.64 | Focus: Diet/Exercise | est_c=0.68",
    "user_utterance": "좋아요. 식단은 4시간 간격 유지하고, 한 끼에 단백질 25–30g, 섬유질 5–8g 추가 계획은 실천 가능해 보여요. 다이어트로 욕구 강도는 지금 High 쪽으로 느껴지지만, 간식 한 번으로 조절하는 방향은 구체적이어서 도전해볼게요. 밤 간식 방지 전략도 바로 적용 가능하고, 지금 욕구는 High에서 점차 낮춰가고 있어요.",
    "suggestion_numeric": 3.6436003117411144
  },
  {
    "turn": 9,
    "agent_utterance": "좋아요. 현재 수준 2.95에 맞춰, 욕구를 점진적으로 낮추고 채택 가능한 구체 계획을 제시합니다. 목표는 4시간 간격 식사 유지와 한 끼 당 단백질 25–30g, 섬유질 5–8g를 안정적으로 지키는 것입니다.\n\n1) 식단 계획 (대략 4시간 간격, High에서 Moderate로 접근)\n- 식사 간격: 4시간 간격 유지. 예시: 8:00, 12:00, 16:00, 20:00\n- 한 끼당 단백질 25–30g, 섬유질 5–8g를 목표로 구성\n- 간식 관리: 간식은 고르게 조절하되, 필요 시 미리 정해둔 “작은 실천 간식”으로 대체\n- 수분: 식사 30분 전 물 한 잔, 식사 중 물 섭취는 필요 시만\n\n구체적 식단 예시\n- 8:00 아침: 계란 2개(약 12g 단백질) + 그릭요거트 150g(약 12g) + 귀리 30g(섬유질 4–5g) +",
    "agent_monologue": "Level 3.64 | Focus: Diet/Exercise | est_c=0.68",
    "user_utterance": "좋아. 지금 식단 계획이 현실적이고 목표도 구체적이어서 동기 부여가 잘 될 듯해. 식단 예시 보니 단백질과 섬유질 목표에 가까워지고 있어. 현재 욕구는 High인데 좀 더 낮추려 애쓰자. 4시간 간격 유지가 마음에 들어. 간식은 미리 정해둔 작은 실천 간식으로 대체하는 방식도 좋아 보돼.",
    "suggestion_numeric": 3.6436003117411144
  }
]